figpack_spike_sorting/__init__.py
figpack_spike_sorting/figpack_spike_sorting.js
figpack_spike_sorting/spike_sorting_extension.py
figpack_spike_sorting/style.css
figpack_spike_sorting/views/AutocorrelogramItem.py
figpack_spike_sorting/views/Autocorrelograms.py
figpack_spike_sorting/views/AverageWaveforms.py
figpack_spike_sorting/views/CrossCorrelogramItem.py
figpack_spike_sorting/views/CrossCorrelograms.py
figpack_spike_sorting/views/RasterPlot.py
figpack_spike_sorting/views/RasterPlotItem.py
figpack_spike_sorting/views/SortingCuration.py
figpack_spike_sorting/views/SpikeAmplitudes.py
figpack_spike_sorting/views/SpikeAmplitudesItem.py
figpack_spike_sorting/views/UnitLocations.py
figpack_spike_sorting/views/UnitMetricsGraph.py
figpack_spike_sorting/views/UnitSimilarityScore.py
figpack_spike_sorting/views/UnitsTable.py
figpack_spike_sorting/views/UnitsTableColumn.py
figpack_spike_sorting/views/UnitsTableRow.py
figpack_spike_sorting/views/__init__.py
figpack_spike_sorting-0.1.7.dist-info/METADATA
figpack_spike_sorting-0.1.7.dist-info/WHEEL
figpack_spike_sorting-0.1.7.dist-info/top_level.txt
figpack_spike_sorting-0.1.7.dist-info/RECORD
